Metadata-Version: 1.0
Name: dist-mh2065
Version: 1.2
Summary: Gaussian and Binomial distributions
Home-page: UNKNOWN
Author: Michael Hartmann
Author-email: mikehartmann@gmx.net
License: UNKNOWN
Platform: UNKNOWN
